[
  {
    "name": "KALOS ft  KORA L - No busco ná (Prod BloodSoul Beats)",
    "link": "https://www.youtube.com/watch?v=cUIrwKdfwBU"
  },
  {
    "name": "Golpe de Ajo - Vuestra Bandera (Con Efecto Guillotina) [Lyric video 2019]",
    "link": "https://www.youtube.com/watch?v=qagGmFLrjZY"
  },
  {
    "name": "Efecto Bumerán - Alternativa libertaria",
    "link": "https://www.youtube.com/watch?v=XIm4_ETBkho"
  },
  {
    "name": "Efecto Bumerán - Bailarán los valientes",
    "link": "https://www.youtube.com/watch?v=AzOY4pKepqw"
  },
  {
    "name": "Juanita la Bandolera - Efecto Bumerán con Dani Carroña (cover)",
    "link": "https://www.youtube.com/watch?v=HfaI3gY4nr4"
  },
  {
    "name": "Efecto Bumerán: Juanita la bandolera - Carroña (cover)",
    "link": "https://www.youtube.com/watch?v=EM6K9Hf_aPM"
  },
  {
    "name": "Efecto Bumerán",
    "link": "https://www.youtube.com/watch?v=GG3ujMOrn8o"
  },
  {
    "name": "Efecto Guillotina - Ser",
    "link": "https://www.youtube.com/watch?v=jRIivYXd-34"
  },
  {
    "name": "Que te vaya bien - Efecto Bumerán & Frade y los Sanmigueles (NDLH cover)",
    "link": "https://www.youtube.com/watch?v=b1-VJG4icMI"
  },
  {
    "name": "El Niño De La Hipoteca - Alquitrán y Carmín cover",
    "link": "https://www.youtube.com/watch?v=hV_Q72K_xYI"
  },
  {
    "name": "Ceremonia - Mala Reputación (cover)",
    "link": "https://www.youtube.com/watch?v=Hn5H9L8hybQ"
  }
]